sigmaconsolemenu/__init__.py
sigmaconsolemenu/helpers.py
sigmaconsolemenu/menu_option.py
sigmaconsolemenu/page.py
sigmaconsolemenu/pointer.py
sigmaconsolemenu/sigma_console_menu.py
sigma_console_menu-0.1.dist-info/LICENSE
sigma_console_menu-0.1.dist-info/METADATA
sigma_console_menu-0.1.dist-info/WHEEL
sigma_console_menu-0.1.dist-info/top_level.txt
sigma_console_menu-0.1.dist-info/RECORD
