Metadata-Version: 2.1
Name: sigma-console-menu
Version: 0.1
Summary: Sigma console menu
Author: Karol Angrys
Author-email: karol.angrys@gmail.com
License: MIT
License-File: LICENSE
Requires-Dist: keyboard
